speechmatics/__init__.py
speechmatics/batch/__init__.py
speechmatics/batch/_async_client.py
speechmatics/batch/_auth.py
speechmatics/batch/_exceptions.py
speechmatics/batch/_helpers.py
speechmatics/batch/_logging.py
speechmatics/batch/_models.py
speechmatics/batch/_transport.py
speechmatics_batch-0.4.4.dist-info/METADATA
speechmatics_batch-0.4.4.dist-info/WHEEL
speechmatics_batch-0.4.4.dist-info/top_level.txt
speechmatics_batch-0.4.4.dist-info/RECORD
