Metadata-Version: 2.4
Name: speechmatics-batch
Version: 0.4.4
Summary: Speechmatics Batch API Client
Author-email: Speechmatics <support@speechmatics.com>
License-Expression: MIT
Project-URL: homepage, https://github.com/speechmatics/speechmatics-python-sdk
Project-URL: documentation, https://docs.speechmatics.com/
Project-URL: repository, https://github.com/speechmatics/speechmatics-python-sdk
Project-URL: issues, https://github.com/speechmatics/speechmatics-python-sdk/issues
Keywords: speechmatics,speech-to-text,batch,transcription,api
Classifier: Development Status :: 4 - Beta
Classifier: Intended Audience :: Developers
Classifier: Programming Language :: Python :: 3
Classifier: Programming Language :: Python :: 3.9
Classifier: Programming Language :: Python :: 3.10
Classifier: Programming Language :: Python :: 3.11
Classifier: Programming Language :: Python :: 3.12
Classifier: Operating System :: OS Independent
Classifier: Topic :: Multimedia :: Sound/Audio :: Speech
Classifier: Topic :: Software Development :: Libraries :: Python Modules
Requires-Python: >=3.9
Requires-Dist: aiohttp
Requires-Dist: aiofiles
Provides-Extra: dev
Requires-Dist: black; extra == "dev"
Requires-Dist: ruff; extra == "dev"
Requires-Dist: mypy; extra == "dev"
Requires-Dist: types-aiofiles; extra == "dev"
Requires-Dist: pre-commit; extra == "dev"
Requires-Dist: pytest; extra == "dev"
Requires-Dist: pytest-asyncio; extra == "dev"
Requires-Dist: pytest-cov; extra == "dev"
Requires-Dist: pytest-mock; extra == "dev"
Requires-Dist: build; extra == "dev"
